text_det_metric/__init__.py
text_det_metric/main.py
text_det_metric-0.0.8.dist-info/LICENSE
text_det_metric-0.0.8.dist-info/METADATA
text_det_metric-0.0.8.dist-info/WHEEL
text_det_metric-0.0.8.dist-info/entry_points.txt
text_det_metric-0.0.8.dist-info/top_level.txt
text_det_metric-0.0.8.dist-info/RECORD
