Metadata-Version: 2.1
Name: text-det-metric
Version: 0.0.8
Summary: Tool of computing the metric of text detection
Home-page: https://github.com/SWHL/TextDetMetric
Author: SWHL
Author-email: liekkaskono@163.com
License: Apache-2.0
Keywords: ocr, text-det, hmean
Platform: Any
Classifier: Programming Language :: Python :: 3.6
Classifier: Programming Language :: Python :: 3.7
Classifier: Programming Language :: Python :: 3.8
Classifier: Programming Language :: Python :: 3.9
Classifier: Programming Language :: Python :: 3.10
Classifier: Programming Language :: Python :: 3.11
Requires-Python: >=3.6,<3.12
Requires-Dist: Shapely
Requires-Dist: datasets
